{"nm":"Untitled file","ddd":0,"h":500,"w":500,"meta":{"g":"@lottiefiles/creator 1.10.0"},"layers":[{"ty":0,"nm":" Vector Smart Object6","sr":1,"st":0,"op":240,"ip":0,"hd":false,"ddd":0,"bm":0,"hasMask":false,"ao":0,"ks":{"a":{"a":0,"k":[300,294.4008]},"s":{"a":0,"k":[84,84]},"sk":{"a":0,"k":0},"p":{"a":0,"k":[252,247.296672]},"r":{"a":0,"k":0},"sa":{"a":0,"k":0},"o":{"a":0,"k":100}},"w":600,"h":600,"refId":"precomp_Vector Smart Object6_6ff96a68-040b-4228-8c8f-d96ba3ad3db3_249fe0e9-5c25-4ac3-b4e4-5ce1d70c5498","ind":1}],"v":"5.7.0","fr":30,"op":240,"ip":0,"assets":[{"nm":"Vector Smart Object6","id":"precomp_Vector Smart Object6_6ff96a68-040b-4228-8c8f-d96ba3ad3db3_249fe0e9-5c25-4ac3-b4e4-5ce1d70c5498","fr":60,"layers":[{"ty":4,"nm":"like Outlines","sr":1,"st":22,"op":193,"ip":22,"hd":false,"ddd":0,"bm":0,"hasMask":false,"ao":0,"ks":{"a":{"a":0,"k":[55.868,442.556,0],"ix":1},"s":{"a":1,"k":[{"o":{"x":0.49,"y":0},"i":{"x":0.51,"y":1},"s":[0,0,100],"t":22},{"o":{"x":0.49,"y":0},"i":{"x":0.51,"y":1},"s":[18,18,100],"t":39},{"o":{"x":0.167,"y":0.167},"i":{"x":0.833,"y":0.833},"s":[16.8,16.8,100],"t":51.00000578377899},{"o":{"x":0.167,"y":0.167},"i":{"x":0.833,"y":0.833},"s":[16.8,16.8],"t":55},{"s":[16.8,16.8],"t":64}],"ix":6},"sk":{"a":0,"k":0},"p":{"a":0,"k":[268,319],"ix":2},"r":{"a":0,"k":0,"ix":10},"sa":{"a":0,"k":0},"o":{"a":0,"k":100,"ix":11}},"shapes":[{"ty":"gr","bm":0,"hd":false,"mn":"ADBE Vector Group","nm":"Group 1","ix":1,"cix":2,"np":7,"it":[{"ty":"sh","bm":0,"hd":false,"mn":"ADBE Vector Shape - Group","nm":"Path 1","ix":1,"d":1,"ks":{"a":0,"k":{"c":true,"i":[[4.453,-29.243],[3.409,-4.861],[10.249,-0.753],[0,0],[4.643,7.397],[3.69,3.269],[5.234,0],[0,0],[0,0],[0,0],[-0.44,6.287],[-23.576,23.576],[-2.095,2.071],[0.875,32.075],[-10.737,0],[0,-10.75],[-0.001,-0.1],[-0.005,-0.1],[5.49,-12.59],[-4.971,-8.797],[-7.699,-1.013],[-0.524,0],[0,0],[-1.031,-15.974]],"o":[[-0.008,0.045],[-4.876,6.955],[-7.354,0.541],[-0.879,-0.014],[-1.657,-2.643],[-9.706,-8.598],[0,0],[0.001,-0.091],[0,0],[6.303,0],[0.024,-0.342],[2.453,-2.454],[23.025,-22.748],[0.02,-10.732],[10.751,0],[0,0.1],[0.003,0.099],[1.446,29.275],[-4.484,10.281],[4.529,8.016],[0.521,0.068],[0,0],[3.798,0.66],[1.41,21.822]],"v":[[159.207,124.757],[154.857,134.47],[132.064,146.086],[16.858,146.925],[2.073,140.032],[-5.563,130.983],[-38.337,121.717],[-88.441,121.717],[-88.434,9.469],[-33.418,9.469],[-21.447,-1.695],[4.792,-59.765],[11.609,-66.531],[39.214,-128.01],[58.709,-147.468],[78.206,-127.971],[78.221,-127.674],[78.221,-127.379],[65.881,-66.488],[62.498,-38.531],[84.146,-27.311],[85.712,-27.208],[153.021,-27.208],[173.485,-6.89]]},"ix":2}},{"ty":"sh","bm":0,"hd":false,"mn":"ADBE Vector Shape - Group","nm":"Path 2","ix":2,"d":1,"ks":{"a":0,"k":{"c":true,"i":[[0.021,0.229],[0,0]],"o":[[0,0],[-0.016,0.183]],"v":[[-88.569,9.47],[-88.514,9.47]]},"ix":2}},{"ty":"sh","bm":0,"hd":false,"mn":"ADBE Vector Shape - Group","nm":"Path 3","ix":3,"d":1,"ks":{"a":0,"k":{"c":true,"i":[[0,0],[4.411,0],[0,0],[0,4.411],[0,0],[-4.411,0],[0,0],[0,-4.411]],"o":[[0,4.411],[0,0],[-4.411,0],[0,0],[0,-4.411],[0,0],[4.411,0],[0,0]],"v":[[-112.434,121.462],[-120.434,129.462],[-167.301,129.462],[-175.301,121.462],[-175.301,12.337],[-167.301,4.337],[-120.434,4.337],[-112.434,12.337]]},"ix":2}},{"ty":"sh","bm":0,"hd":false,"mn":"ADBE Vector Shape - Group","nm":"Path 4","ix":4,"d":1,"ks":{"a":0,"k":{"c":true,"i":[[1.865,28.869],[13.697,1.679],[0.487,0],[0,0],[0.314,0.052],[-0.778,1.785],[1.724,34.895],[0,0.002],[23.784,0],[0,-23.984],[-0.001,-0.058],[-0.002,-0.058],[20.338,-20.093],[2.491,-2.49],[2.904,-14.798],[0,0],[6.392,0],[0,0],[0,-17.645],[0,0],[-17.644,0],[0,0],[-5.6,4.81],[0,0],[-2.613,-2.702],[-1.334,-1.914],[-3.95,-0.06],[-0.062,0],[-7.375,0.543],[-1.982,13.292]],"o":[[-1.933,-29.924],[-0.482,-0.06],[0,0],[-0.357,-0.052],[0.701,-1.745],[5.997,-13.753],[0,-0.002],[-0.321,-23.709],[-23.984,0],[0,0.058],[0.001,0.058],[0.657,23.147],[-2.129,2.104],[-20.809,20.811],[0,0],[-5.003,-3.242],[0,0],[-17.645,0],[0,0],[0,17.645],[0,0],[7.945,0],[0,0],[6.521,0.153],[1.461,1.294],[12.127,17.382],[0.061,0.002],[0,0],[34.305,-2.521],[0.669,-4.392]],"v":[[197.436,-8.437],[155.394,-51.12],[153.936,-51.209],[86.535,-51.209],[85.528,-51.365],[87.881,-56.896],[102.191,-128.562],[102.19,-128.568],[58.71,-171.467],[15.213,-127.97],[15.222,-127.799],[15.218,-127.629],[-5.257,-83.605],[-12.18,-76.736],[-43.768,-14.531],[-103.084,-14.531],[-120.434,-19.664],[-167.301,-19.664],[-199.301,12.336],[-199.301,121.461],[-167.301,153.461],[-120.434,153.461],[-99.617,145.734],[-37.446,145.734],[-21.477,148.949],[-17.75,153.563],[16.577,170.924],[16.762,170.924],[133.825,170.924],[182.937,128.334]]},"ix":2}},{"ty":"mm","bm":0,"hd":false,"mn":"ADBE Vector Filter - Merge","nm":"Merge Paths 1","mm":1},{"ty":"st","bm":0,"hd":false,"mn":"ADBE Vector Graphic - Stroke","nm":"Stroke 1","lc":1,"lj":1,"ml":10,"o":{"a":0,"k":100,"ix":4},"w":{"a":0,"k":6,"ix":5},"c":{"a":0,"k":[0,0,0],"ix":3}},{"ty":"fl","bm":0,"hd":false,"mn":"ADBE Vector Graphic - Fill","nm":"Fill 1","c":{"a":0,"k":[0.3608,0.8941,0.0157],"ix":4},"r":1,"o":{"a":0,"k":100,"ix":5}},{"ty":"tr","a":{"a":0,"k":[-0.9324951171875,-0.15421295166015625],"ix":1},"s":{"a":0,"k":[100,100],"ix":3},"sk":{"a":0,"k":0,"ix":4},"p":{"a":0,"k":[254.2365048828125,271.23678704833986],"ix":2},"r":{"a":0,"k":0,"ix":6},"sa":{"a":0,"k":0,"ix":5},"o":{"a":0,"k":100,"ix":7}}]},{"ty":"gr","bm":0,"hd":false,"mn":"ADBE Vector Group","nm":"Group 2","ix":2,"cix":2,"np":2,"it":[{"ty":"sh","bm":0,"hd":false,"mn":"ADBE Vector Shape - Group","nm":"Path 1","ix":1,"d":1,"ks":{"a":0,"k":{"c":true,"i":[[4.411,0],[0,0],[0,-4.411],[0,0],[-4.411,0],[0,0],[0,4.411],[0,0]],"o":[[0,0],[-4.411,0],[0,0],[0,4.411],[0,0],[4.411,0],[0,0],[0,-4.411]],"v":[[23.434,-62.563],[-23.434,-62.563],[-31.434,-54.563],[-31.434,54.563],[-23.434,62.563],[23.434,62.563],[31.434,54.563],[31.434,-54.563]]},"ix":2}},{"ty":"fl","bm":0,"hd":false,"mn":"ADBE Vector Graphic - Fill","nm":"Fill 1","c":{"a":0,"k":[0.8471,0.0941,0.2824],"ix":4},"r":1,"o":{"a":0,"k":100,"ix":5}},{"ty":"tr","a":{"a":0,"k":[2.2737367544323206e-13,0],"ix":1},"s":{"a":0,"k":[100,100],"ix":3},"sk":{"a":0,"k":0,"ix":4},"p":{"a":0,"k":[111.30100000000023,338.29],"ix":2},"r":{"a":0,"k":0,"ix":6},"sa":{"a":0,"k":0,"ix":5},"o":{"a":0,"k":100,"ix":7}}]}],"ind":1},{"ty":4,"nm":"Layer 4 Outlines","sr":1,"st":0,"op":79,"ip":0,"hd":false,"ddd":0,"bm":0,"hasMask":false,"ao":0,"ks":{"a":{"a":0,"k":[56.833,1.5,0],"ix":1},"s":{"a":1,"k":[{"o":{"x":1,"y":0},"i":{"x":0.78,"y":1},"s":[0,120,100],"t":0},{"o":{"x":0.22,"y":0},"i":{"x":0.28,"y":1},"s":[139.2,120,100],"t":17},{"o":{"x":0.72,"y":0},"i":{"x":0.833,"y":1},"s":[120,120,100],"t":26},{"o":{"x":0.167,"y":0},"i":{"x":0.833,"y":1},"s":[120,120,100],"t":93},{"s":[0,120,100],"t":108.000005132085}],"ix":6},"sk":{"a":0,"k":0},"p":{"a":1,"k":[{"o":{"x":0.23,"y":0},"i":{"x":0.77,"y":1},"s":[300.3612,294.39959999999996,0],"t":26},{"o":{"x":0.23,"y":0},"i":{"x":0.77,"y":1},"s":[300.3612,222.39960000000002,0],"t":40},{"o":{"x":0.23,"y":0},"i":{"x":0.77,"y":1},"s":[300.3612,372.3996,0],"t":66},{"o":{"x":0.167,"y":0.167},"i":{"x":0.833,"y":0.833},"s":[300,265],"t":81},{"o":{"x":0.167,"y":0.167},"i":{"x":0.833,"y":0.833},"s":[300,245],"t":84},{"o":{"x":0.167,"y":0.167},"i":{"x":0.833,"y":0.833},"s":[300,225],"t":87},{"o":{"x":0.167,"y":0.167},"i":{"x":0.833,"y":0.833},"s":[300,212],"t":89},{"o":{"x":0.167,"y":0.167},"i":{"x":0.833,"y":0.833},"s":[300,199],"t":91},{"o":{"x":0.167,"y":0.167},"i":{"x":0.833,"y":0.833},"s":[300,192],"t":92},{"o":{"x":0.167,"y":0.167},"i":{"x":0.833,"y":0.833},"s":[300,185],"t":93},{"o":{"x":0.167,"y":0.167},"i":{"x":0.833,"y":0.833},"s":[250.301,185.333,0],"t":93.000004521123},{"o":{"x":0.167,"y":0.167},"i":{"x":0.833,"y":0.833},"s":[300,185],"t":94},{"o":{"x":0.167,"y":0.167},"i":{"x":0.833,"y":0.833},"s":[300,250],"t":99},{"o":{"x":0.167,"y":0.167},"i":{"x":0.833,"y":0.833},"s":[300,185],"t":115},{"s":[299,185],"t":134}],"ix":2},"r":{"a":0,"k":0,"ix":10},"sa":{"a":0,"k":0},"o":{"a":0,"k":100,"ix":11}},"shapes":[{"ty":"gr","bm":0,"hd":false,"mn":"ADBE Vector Group","nm":"Group 1","ix":1,"cix":2,"np":2,"it":[{"ty":"sh","bm":0,"hd":false,"mn":"ADBE Vector Shape - Group","nm":"Path 1","ix":1,"d":1,"ks":{"a":0,"k":{"c":false,"i":[[0,0],[0,0]],"o":[[0,0],[0,0]],"v":[[1.5,1.5],[112.167,1.5]]},"ix":2}},{"ty":"st","bm":0,"hd":false,"mn":"ADBE Vector Graphic - Stroke","nm":"Stroke 1","lc":2,"lj":1,"ml":10,"o":{"a":0,"k":100,"ix":4},"w":{"a":0,"k":5,"ix":5},"c":{"a":0,"k":[0.8471,0.0941,0.2824],"ix":3}},{"ty":"tr","a":{"a":0,"k":[0,0],"ix":1},"s":{"a":0,"k":[100,100],"ix":3},"sk":{"a":0,"k":0,"ix":4},"p":{"a":0,"k":[0,0],"ix":2},"r":{"a":0,"k":0,"ix":6},"sa":{"a":0,"k":0,"ix":5},"o":{"a":0,"k":100,"ix":7}}]}],"ind":2},{"ty":4,"nm":"Layer 2 Outlines","sr":1,"st":0,"op":240.0000097754,"ip":0,"hd":false,"ddd":0,"bm":0,"hasMask":true,"ao":0,"ks":{"a":{"a":0,"k":[51,89.333,0],"ix":1},"s":{"a":1,"k":[{"o":{"x":0.19,"y":0},"i":{"x":0.81,"y":1},"s":[120,120,100],"t":118},{"o":{"x":0.19,"y":0},"i":{"x":0.81,"y":1},"s":[136.79999999999998,136.79999999999998,100],"t":130},{"s":[116.40000000000002,116.40000000000002,100],"t":142.000005783779}],"ix":6},"sk":{"a":0,"k":0},"p":{"a":0,"k":[300,294.39959999999996,0],"ix":2},"r":{"a":0,"k":0,"ix":10},"sa":{"a":0,"k":0},"o":{"a":0,"k":100,"ix":11}},"masksProperties":[{"nm":"Mask 1","inv":false,"mode":"a","x":{"a":0,"k":0,"ix":4},"o":{"a":0,"k":100,"ix":3},"pt":{"a":1,"k":[{"o":{"x":0.7,"y":0},"i":{"x":0.3,"y":1},"s":[{"c":true,"i":[[0,0],[0,0],[0,0],[0,0]],"o":[[0,0],[0,0],[0,0],[0,0]],"v":[[118.5,-42],[-17,-42],[-17,0.5],[118.5,0.5]]}],"t":0},{"s":[{"c":true,"i":[[0,0],[0,0],[0,0],[0,0]],"o":[[0,0],[0,0],[0,0],[0,0]],"v":[[118.5,-42],[-17,-42],[-17,180.5],[118.5,180.5]]}],"t":29.0000011811942}],"ix":1}}],"shapes":[{"ty":"gr","bm":0,"hd":false,"mn":"ADBE Vector Group","nm":"Group 1","ix":1,"cix":2,"np":5,"it":[{"ty":"sh","bm":0,"hd":false,"mn":"ADBE Vector Shape - Group","nm":"Path 1","ix":1,"d":1,"ks":{"a":0,"k":{"c":true,"i":[[0,0],[5.055,0],[0,0],[0,5.055],[0,0],[-5.055,0],[0,0],[0,0],[-2.382,0],[0,0],[0,2.381],[0,0],[0,0],[0,-5.055]],"o":[[0,5.055],[0,0],[-5.055,0],[0,0],[0,-5.055],[0,0],[0,0],[0,2.381],[0,0],[2.382,0],[0,0],[0,0],[5.055,0],[0,0]],"v":[[43.5,72.667],[34.333,81.834],[-34.333,81.834],[-43.5,72.667],[-43.5,-72.666],[-34.333,-81.834],[-13.813,-81.834],[-13.813,-78.395],[-9.5,-74.084],[9.5,-74.084],[13.813,-78.395],[13.813,-81.834],[34.333,-81.834],[43.5,-72.666]]},"ix":2}},{"ty":"sh","bm":0,"hd":false,"mn":"ADBE Vector Shape - Group","nm":"Path 2","ix":2,"d":1,"ks":{"a":0,"k":{"c":true,"i":[[7.812,0],[0,0],[0,-7.812],[0,0],[-7.812,0],[0,0],[0,7.812],[0,0]],"o":[[0,0],[-7.812,0],[0,0],[0,7.812],[0,0],[7.812,0],[0,0],[0,-7.812]],"v":[[34.333,-86.834],[-34.333,-86.834],[-48.5,-72.666],[-48.5,72.667],[-34.333,86.834],[34.333,86.834],[48.5,72.667],[48.5,-72.666]]},"ix":2}},{"ty":"mm","bm":0,"hd":false,"mn":"ADBE Vector Filter - Merge","nm":"Merge Paths 1","mm":1},{"ty":"st","bm":0,"hd":false,"mn":"ADBE Vector Graphic - Stroke","nm":"Stroke 1","lc":1,"lj":1,"ml":10,"o":{"a":0,"k":100,"ix":4},"w":{"a":0,"k":2,"ix":5},"c":{"a":0,"k":[0.0941,0.2196,0.3137],"ix":3}},{"ty":"fl","bm":0,"hd":false,"mn":"ADBE Vector Graphic - Fill","nm":"Fill 1","c":{"a":0,"k":[0.9412,0.9098,0.9412],"ix":4},"r":1,"o":{"a":0,"k":100,"ix":5}},{"ty":"tr","a":{"a":0,"k":[0,0],"ix":1},"s":{"a":0,"k":[100,100],"ix":3},"sk":{"a":0,"k":0,"ix":4},"p":{"a":0,"k":[51,89.334],"ix":2},"r":{"a":0,"k":0,"ix":6},"sa":{"a":0,"k":0,"ix":5},"o":{"a":0,"k":100,"ix":7}}]}],"ind":3},{"ty":4,"nm":"Layer 3 Outlines","sr":1,"st":0,"op":240.0000097754,"ip":0,"hd":false,"ddd":0,"bm":0,"hasMask":true,"ao":0,"ks":{"a":{"a":0,"k":[46.25,84.584,0],"ix":1},"s":{"a":1,"k":[{"o":{"x":0.19,"y":0},"i":{"x":0.81,"y":1},"s":[120,120,100],"t":118},{"o":{"x":0.19,"y":0},"i":{"x":0.81,"y":1},"s":[136.79999999999998,136.79999999999998,100],"t":130},{"s":[116.40000000000002,116.40000000000002,100],"t":142.000005783779}],"ix":6},"sk":{"a":0,"k":0},"p":{"a":0,"k":[300,294.4008,0],"ix":2},"r":{"a":0,"k":0,"ix":10},"sa":{"a":0,"k":0},"o":{"a":0,"k":100,"ix":11}},"masksProperties":[{"nm":"Mask 1","inv":false,"mode":"a","x":{"a":0,"k":0,"ix":4},"o":{"a":0,"k":100,"ix":3},"pt":{"a":1,"k":[{"o":{"x":0.99,"y":0},"i":{"x":0.01,"y":1},"s":[{"c":true,"i":[[0,0],[0,0],[0,0],[0,0]],"o":[[0,0],[0,0],[0,0],[0,0]],"v":[[96.25,171.25],[-4.75,171.25],[-4.75,174.25],[96.25,174.25]]}],"t":5},{"s":[{"c":true,"i":[[0,0],[0,0],[0,0],[0,0]],"o":[[0,0],[0,0],[0,0],[0,0]],"v":[[96.25,-7.25],[-4.75,-7.25],[-4.75,174.25],[96.25,174.25]]}],"t":31.0000012626559}],"ix":1}}],"shapes":[{"ty":"gr","bm":0,"hd":false,"mn":"ADBE Vector Group","nm":"Group 1","ix":1,"cix":2,"np":2,"it":[{"ty":"sh","bm":0,"hd":false,"mn":"ADBE Vector Shape - Group","nm":"Path 1","ix":1,"d":1,"ks":{"a":0,"k":{"c":true,"i":[[6.443,0],[0,0],[0,6.443],[0,0],[-6.443,0],[0,0],[0,-6.444],[0,0]],"o":[[0,0],[-6.443,0],[0,0],[0,-6.444],[0,0],[6.443,0],[0,0],[0,6.443]],"v":[[34.333,84.334],[-34.334,84.334],[-46,72.667],[-46,-72.666],[-34.334,-84.334],[34.333,-84.334],[46,-72.666],[46,72.667]]},"ix":2}},{"ty":"fl","bm":0,"hd":false,"mn":"ADBE Vector Graphic - Fill","nm":"Fill 1","c":{"a":0,"k":[0.0941,0.2196,0.3137],"ix":4},"r":1,"o":{"a":0,"k":100,"ix":5}},{"ty":"tr","a":{"a":0,"k":[0,0],"ix":1},"s":{"a":0,"k":[100,100],"ix":3},"sk":{"a":0,"k":0,"ix":4},"p":{"a":0,"k":[46.25,84.584],"ix":2},"r":{"a":0,"k":0,"ix":6},"sa":{"a":0,"k":0,"ix":5},"o":{"a":0,"k":100,"ix":7}}]}],"ind":4},{"ty":4,"nm":"Shape Layer 2","sr":1,"st":0,"op":240.0000097754,"ip":0,"hd":false,"ddd":0,"bm":0,"hasMask":false,"ao":0,"ks":{"a":{"a":0,"k":[0,-0.5,0],"ix":1},"s":{"a":1,"k":[{"o":{"x":0.34,"y":0},"i":{"x":0.66,"y":1},"s":[0,0,100],"t":0},{"o":{"x":0.34,"y":0},"i":{"x":0.66,"y":1},"s":[129.6,129.6,100],"t":15},{"o":{"x":0.34,"y":0},"i":{"x":0.833,"y":1},"s":[120,120,100],"t":26},{"o":{"x":0.167,"y":0},"i":{"x":0.833,"y":1},"s":[142.8,142.8,100],"t":43},{"o":{"x":0.167,"y":0},"i":{"x":0.833,"y":1},"s":[133.20000000000002,133.20000000000002,100],"t":64},{"o":{"x":0.167,"y":0},"i":{"x":0.833,"y":1},"s":[139.2,139.2,100],"t":88},{"o":{"x":0.167,"y":0},"i":{"x":0.833,"y":1},"s":[132,132,100],"t":118},{"o":{"x":0.167,"y":0},"i":{"x":0.66,"y":1},"s":[141.6,141.6,100],"t":152},{"o":{"x":0.34,"y":0},"i":{"x":0.833,"y":1},"s":[120,120,100],"t":172},{"o":{"x":0.167,"y":0},"i":{"x":0.833,"y":1},"s":[142.8,142.8,100],"t":189},{"o":{"x":0.167,"y":0},"i":{"x":0.833,"y":1},"s":[133.20000000000002,133.20000000000002,100],"t":210},{"s":[139.2,139.2,100],"t":239.00000973467}],"ix":6},"sk":{"a":0,"k":0},"p":{"a":0,"k":[300,299.4,0],"ix":2},"r":{"a":0,"k":0,"ix":10},"sa":{"a":0,"k":0},"o":{"a":0,"k":51,"ix":11}},"shapes":[{"ty":"gr","bm":0,"hd":false,"mn":"ADBE Vector Group","nm":"Ellipse 1","ix":1,"cix":2,"np":3,"it":[{"ty":"el","bm":0,"hd":false,"mn":"ADBE Vector Shape - Ellipse","nm":"Ellipse Path 1","d":1,"p":{"a":0,"k":[0,0],"ix":3},"s":{"a":0,"k":[242,242],"ix":2}},{"ty":"st","bm":0,"hd":false,"mn":"ADBE Vector Graphic - Stroke","nm":"Stroke 1","lc":1,"lj":1,"ml":4,"o":{"a":0,"k":100,"ix":4},"w":{"a":0,"k":0,"ix":5},"c":{"a":0,"k":[0.6902,0.4471,0.4471],"ix":3}},{"ty":"fl","bm":0,"hd":false,"mn":"ADBE Vector Graphic - Fill","nm":"Fill 1","c":{"a":0,"k":[0.4392,0.5961,0.6588],"ix":4},"r":1,"o":{"a":0,"k":100,"ix":5}},{"ty":"tr","a":{"a":0,"k":[0,0],"ix":1},"s":{"a":0,"k":[100,100],"ix":3},"sk":{"a":0,"k":0,"ix":4},"p":{"a":0,"k":[0,-0.5],"ix":2},"r":{"a":0,"k":0,"ix":6},"sa":{"a":0,"k":0,"ix":5},"o":{"a":0,"k":100,"ix":7}}]}],"ind":5},{"ty":4,"nm":"Shape Layer 3","sr":1,"st":0,"op":240.0000097754,"ip":0,"hd":false,"ddd":0,"bm":0,"hasMask":false,"ao":0,"ks":{"a":{"a":0,"k":[0,-0.5,0],"ix":1},"s":{"a":1,"k":[{"o":{"x":0.34,"y":0},"i":{"x":0.66,"y":1},"s":[0,0,100],"t":0},{"o":{"x":0.34,"y":0},"i":{"x":0.833,"y":1},"s":[168,168,100],"t":26},{"o":{"x":0.167,"y":0},"i":{"x":0.833,"y":1},"s":[190.8,190.8,100],"t":51},{"o":{"x":0.167,"y":0},"i":{"x":0.833,"y":1},"s":[181.2,181.2,100],"t":75},{"o":{"x":0.167,"y":0},"i":{"x":0.833,"y":1},"s":[187.2,187.2,100],"t":101},{"o":{"x":0.167,"y":0},"i":{"x":0.833,"y":1},"s":[180,180,100],"t":122},{"o":{"x":0.167,"y":0},"i":{"x":0.66,"y":1},"s":[189.6,189.6,100],"t":146},{"o":{"x":0.34,"y":0},"i":{"x":0.833,"y":1},"s":[168,168,100],"t":172},{"o":{"x":0.167,"y":0},"i":{"x":0.833,"y":1},"s":[190.8,190.8,100],"t":195},{"o":{"x":0.167,"y":0},"i":{"x":0.833,"y":1},"s":[181.2,181.2,100],"t":218},{"s":[187.2,187.2,100],"t":239.00000973467}],"ix":6},"sk":{"a":0,"k":0},"p":{"a":0,"k":[300,299.4,0],"ix":2},"r":{"a":0,"k":0,"ix":10},"sa":{"a":0,"k":0},"o":{"a":0,"k":21,"ix":11}},"shapes":[{"ty":"gr","bm":0,"hd":false,"mn":"ADBE Vector Group","nm":"Ellipse 1","ix":1,"cix":2,"np":3,"it":[{"ty":"el","bm":0,"hd":false,"mn":"ADBE Vector Shape - Ellipse","nm":"Ellipse Path 1","d":1,"p":{"a":0,"k":[0,0],"ix":3},"s":{"a":0,"k":[242,242],"ix":2}},{"ty":"st","bm":0,"hd":false,"mn":"ADBE Vector Graphic - Stroke","nm":"Stroke 1","lc":1,"lj":1,"ml":4,"o":{"a":0,"k":100,"ix":4},"w":{"a":0,"k":0,"ix":5},"c":{"a":0,"k":[0.6902,0.4471,0.4471],"ix":3}},{"ty":"fl","bm":0,"hd":false,"mn":"ADBE Vector Graphic - Fill","nm":"Fill 1","c":{"a":0,"k":[0.4392,0.5961,0.6588],"ix":4},"r":1,"o":{"a":0,"k":100,"ix":5}},{"ty":"tr","a":{"a":0,"k":[0,0],"ix":1},"s":{"a":0,"k":[100,100],"ix":3},"sk":{"a":0,"k":0,"ix":4},"p":{"a":0,"k":[0,-0.5],"ix":2},"r":{"a":0,"k":0,"ix":6},"sa":{"a":0,"k":0,"ix":5},"o":{"a":0,"k":100,"ix":7}}]}],"ind":6},{"ty":4,"nm":"Shape Layer 1","sr":1,"st":0,"op":240.0000097754,"ip":0,"hd":false,"ddd":0,"bm":0,"hasMask":false,"ao":0,"ks":{"a":{"a":0,"k":[0,-0.5,0],"ix":1},"s":{"a":1,"k":[{"o":{"x":0.34,"y":0},"i":{"x":0.66,"y":1},"s":[0,0,100],"t":0},{"o":{"x":0.34,"y":0},"i":{"x":0.833,"y":1},"s":[218.4,218.4,100],"t":20},{"o":{"x":0.167,"y":0},"i":{"x":0.833,"y":1},"s":[241.19999999999996,241.19999999999996,100],"t":45},{"o":{"x":0.167,"y":0},"i":{"x":0.833,"y":1},"s":[231.6,231.6,100],"t":69},{"o":{"x":0.167,"y":0},"i":{"x":0.833,"y":1},"s":[237.6,237.6,100],"t":94},{"o":{"x":0.167,"y":0},"i":{"x":0.833,"y":1},"s":[230.40000000000003,230.40000000000003,100],"t":122},{"o":{"x":0.167,"y":0},"i":{"x":0.66,"y":1},"s":[240,240,100],"t":146},{"o":{"x":0.34,"y":0},"i":{"x":0.833,"y":1},"s":[218.4,218.4,100],"t":172},{"o":{"x":0.167,"y":0},"i":{"x":0.833,"y":1},"s":[241.19999999999996,241.19999999999996,100],"t":202},{"o":{"x":0.167,"y":0},"i":{"x":0.833,"y":1},"s":[231.6,231.6,100],"t":225},{"s":[237.6,237.6,100],"t":239.00000973467}],"ix":6},"sk":{"a":0,"k":0},"p":{"a":0,"k":[300,299.4,0],"ix":2},"r":{"a":0,"k":0,"ix":10},"sa":{"a":0,"k":0},"o":{"a":0,"k":21,"ix":11}},"shapes":[{"ty":"gr","bm":0,"hd":false,"mn":"ADBE Vector Group","nm":"Ellipse 1","ix":1,"cix":2,"np":3,"it":[{"ty":"el","bm":0,"hd":false,"mn":"ADBE Vector Shape - Ellipse","nm":"Ellipse Path 1","d":1,"p":{"a":0,"k":[0,0],"ix":3},"s":{"a":0,"k":[242,242],"ix":2}},{"ty":"st","bm":0,"hd":false,"mn":"ADBE Vector Graphic - Stroke","nm":"Stroke 1","lc":1,"lj":1,"ml":4,"o":{"a":0,"k":100,"ix":4},"w":{"a":0,"k":0,"ix":5},"c":{"a":0,"k":[0.6902,0.4471,0.4471],"ix":3}},{"ty":"fl","bm":0,"hd":false,"mn":"ADBE Vector Graphic - Fill","nm":"Fill 1","c":{"a":0,"k":[0.4392,0.5961,0.6588],"ix":4},"r":1,"o":{"a":0,"k":100,"ix":5}},{"ty":"tr","a":{"a":0,"k":[0,0],"ix":1},"s":{"a":0,"k":[100,100],"ix":3},"sk":{"a":0,"k":0,"ix":4},"p":{"a":0,"k":[0,-0.5],"ix":2},"r":{"a":0,"k":0,"ix":6},"sa":{"a":0,"k":0,"ix":5},"o":{"a":0,"k":100,"ix":7}}]}],"ind":7}]}]}